MANIFEST.in
README.md
setup.cfg
setup.py
resystools/__init__.py
resystools.egg-info/PKG-INFO
resystools.egg-info/SOURCES.txt
resystools.egg-info/dependency_links.txt
resystools.egg-info/requires.txt
resystools.egg-info/top_level.txt
resystools/explicite/MovieLens.py
resystools/explicite/__init__.py
resystools/explicite/cfmodel.py
resystools/explicite/Data/__init__.py
resystools/explicite/Data/ml-100k/README
resystools/explicite/Data/ml-100k/__init__.py
resystools/explicite/Data/ml-100k/allbut.pl
resystools/explicite/Data/ml-100k/mku.sh
resystools/explicite/Data/ml-100k/u.data
resystools/explicite/Data/ml-100k/u.genre
resystools/explicite/Data/ml-100k/u.info
resystools/explicite/Data/ml-100k/u.item
resystools/explicite/Data/ml-100k/u.occupation
resystools/explicite/Data/ml-100k/u.user
resystools/explicite/Data/ml-100k/u1.base
resystools/explicite/Data/ml-100k/u1.test
resystools/explicite/Data/ml-100k/u2.base
resystools/explicite/Data/ml-100k/u2.test
resystools/explicite/Data/ml-100k/u3.base
resystools/explicite/Data/ml-100k/u3.test
resystools/explicite/Data/ml-100k/u4.base
resystools/explicite/Data/ml-100k/u4.test
resystools/explicite/Data/ml-100k/u5.base
resystools/explicite/Data/ml-100k/u5.test
resystools/explicite/Data/ml-100k/ua.base
resystools/explicite/Data/ml-100k/ua.test
resystools/explicite/Data/ml-100k/ub.base
resystools/explicite/Data/ml-100k/ub.test
resystools/explicite/Data/ml-1m/README
resystools/explicite/Data/ml-1m/__init__.py
resystools/explicite/Data/ml-1m/movies.dat
resystools/explicite/Data/ml-1m/ratings.dat
resystools/explicite/Data/ml-1m/users.dat
resystools/implicite/ItemKnn.py
resystools/implicite/MovieLens1M.py
resystools/implicite/__init__.py
resystools/implicite/config.py
resystools/implicite/data_utils.py
resystools/implicite/data_utils1.py
resystools/implicite/data_utils2.py
resystools/implicite/data_utils_itempop.py
resystools/implicite/evaluate.py
resystools/implicite/itemKNNidata.py
resystools/implicite/itempop.py
resystools/implicite/main.py
resystools/implicite/model.py
resystools/implicite/Data/__init__.py
resystools/implicite/Data/ml-1m.test.negative
resystools/implicite/Data/ml-1m.test.rating
