Metadata-Version: 1.1
Name: resystools
Version: 0.2.0
Summary: The library supports users implementing recommendation algorithms
Home-page: https://github.com/DucLeTrong/resystools
Author: Trong Duc Le
Author-email: trongduclebk@gmail.com
License: MIT
Keywords: RECOMMENDATION,RECOMMENDER
Platform: UNKNOWN
Classifier: License :: OSI Approved :: MIT License
Classifier: Programming Language :: Python :: 3.4
Classifier: Programming Language :: Python :: 3.5
Classifier: Programming Language :: Python :: 3.6
